{"summaries":[{"symbol":{"__symbol":0,"members":[]},"metadata":{"__symbolic":"class"},"type":{"summaryKind":2,"type":{"reference":{"__symbol":0,"members":[]},"diDeps":[],"lifecycleHooks":[]},"entryComponents":[{"componentType":{"__symbol":1,"members":[]},"componentFactory":{"__symbol":2,"members":[]}},{"componentType":{"__symbol":3,"members":[]},"componentFactory":{"__symbol":4,"members":[]}},{"componentType":{"__symbol":5,"members":[]},"componentFactory":{"__symbol":6,"members":[]}},{"componentType":{"__symbol":7,"members":[]},"componentFactory":{"__symbol":8,"members":[]}},{"componentType":{"__symbol":9,"members":[]},"componentFactory":{"__symbol":10,"members":[]}},{"componentType":{"__symbol":11,"members":[]},"componentFactory":{"__symbol":12,"members":[]}},{"componentType":{"__symbol":13,"members":[]},"componentFactory":{"__symbol":14,"members":[]}}],"providers":[{"provider":{"token":{"identifier":{"reference":{"__symbol":15,"members":[]}}},"useClass":{"reference":{"__symbol":16,"members":[]},"diDeps":[{"isAttribute":false,"isHost":false,"isSelf":false,"isSkipSelf":false,"isOptional":false,"token":{"identifier":{"reference":{"__symbol":17,"members":[]}}}}],"lifecycleHooks":[]},"useFactory":null,"deps":[{"isAttribute":false,"isHost":false,"isSelf":false,"isSkipSelf":false,"isOptional":false,"token":{"identifier":{"reference":{"__symbol":17,"members":[]}}}}],"multi":false},"module":{"reference":{"__symbol":18,"members":[]},"diDeps":[],"lifecycleHooks":[]}},{"provider":{"token":{"identifier":{"reference":{"__symbol":19,"members":[]},"diDeps":[],"lifecycleHooks":[]}},"useClass":{"reference":{"__symbol":19,"members":[]},"diDeps":[],"lifecycleHooks":[]},"useFactory":null,"deps":[],"multi":false},"module":{"reference":{"__symbol":20,"members":[]},"diDeps":[],"lifecycleHooks":[]}},{"provider":{"token":{"identifier":{"reference":{"__symbol":21,"members":[]},"diDeps":[{"isAttribute":false,"isHost":false,"isSelf":false,"isSkipSelf":false,"isOptional":false,"token":{"identifier":{"reference":{"__symbol":22,"members":[]}}}},{"isAttribute":false,"isHost":false,"isSelf":false,"isSkipSelf":false,"isOptional":false,"token":{"identifier":{"reference":{"__symbol":23,"members":[]}}}},{"isAttribute":false,"isHost":false,"isSelf":false,"isSkipSelf":false,"isOptional":false,"token":{"identifier":{"reference":{"__symbol":24,"members":[]}}}}],"lifecycleHooks":[]}},"useClass":{"reference":{"__symbol":21,"members":[]},"diDeps":[{"isAttribute":false,"isHost":false,"isSelf":false,"isSkipSelf":false,"isOptional":false,"token":{"identifier":{"reference":{"__symbol":22,"members":[]}}}},{"isAttribute":false,"isHost":false,"isSelf":false,"isSkipSelf":false,"isOptional":false,"token":{"identifier":{"reference":{"__symbol":23,"members":[]}}}},{"isAttribute":false,"isHost":false,"isSelf":false,"isSkipSelf":false,"isOptional":false,"token":{"identifier":{"reference":{"__symbol":24,"members":[]}}}}],"lifecycleHooks":[]},"useFactory":null,"deps":[{"isAttribute":false,"isHost":false,"isSelf":false,"isSkipSelf":false,"isOptional":false,"token":{"identifier":{"reference":{"__symbol":22,"members":[]}}}},{"isAttribute":false,"isHost":false,"isSelf":false,"isSkipSelf":false,"isOptional":false,"token":{"identifier":{"reference":{"__symbol":23,"members":[]}}}},{"isAttribute":false,"isHost":false,"isSelf":false,"isSkipSelf":false,"isOptional":false,"token":{"identifier":{"reference":{"__symbol":24,"members":[]}}}}],"multi":false},"module":{"reference":{"__symbol":25,"members":[]},"diDeps":[],"lifecycleHooks":[]}},{"provider":{"token":{"identifier":{"reference":{"__symbol":26,"members":[]},"diDeps":[],"lifecycleHooks":[]}},"useClass":{"reference":{"__symbol":26,"members":[]},"diDeps":[],"lifecycleHooks":[]},"useFactory":null,"deps":[],"multi":false},"module":{"reference":{"__symbol":27,"members":[]},"diDeps":[],"lifecycleHooks":[]}},{"provider":{"token":{"identifier":{"reference":{"__symbol":28,"members":[]},"diDeps":[],"lifecycleHooks":[]}},"useClass":{"reference":{"__symbol":28,"members":[]},"diDeps":[],"lifecycleHooks":[]},"useFactory":null,"deps":[],"multi":false},"module":{"reference":{"__symbol":27,"members":[]},"diDeps":[],"lifecycleHooks":[]}},{"provider":{"token":{"identifier":{"reference":{"__symbol":29,"members":[]},"diDeps":[],"lifecycleHooks":[]}},"useClass":{"reference":{"__symbol":29,"members":[]},"diDeps":[],"lifecycleHooks":[]},"useFactory":null,"deps":[],"multi":false},"module":{"reference":{"__symbol":27,"members":[]},"diDeps":[],"lifecycleHooks":[]}},{"provider":{"token":{"identifier":{"reference":{"__symbol":30,"members":[]},"diDeps":[],"lifecycleHooks":[]}},"useClass":{"reference":{"__symbol":30,"members":[]},"diDeps":[],"lifecycleHooks":[]},"useFactory":null,"deps":[],"multi":false},"module":{"reference":{"__symbol":27,"members":[]},"diDeps":[],"lifecycleHooks":[]}},{"provider":{"token":{"identifier":{"reference":{"__symbol":31,"members":[]},"diDeps":[],"lifecycleHooks":[]}},"useClass":{"reference":{"__symbol":31,"members":[]},"diDeps":[],"lifecycleHooks":[]},"useFactory":null,"deps":[],"multi":false},"module":{"reference":{"__symbol":27,"members":[]},"diDeps":[],"lifecycleHooks":[]}},{"provider":{"token":{"identifier":{"reference":{"__symbol":32,"members":[]},"diDeps":[],"lifecycleHooks":[]}},"useClass":{"reference":{"__symbol":32,"members":[]},"diDeps":[],"lifecycleHooks":[]},"useFactory":null,"deps":[],"multi":false},"module":{"reference":{"__symbol":27,"members":[]},"diDeps":[],"lifecycleHooks":[]}},{"provider":{"token":{"identifier":{"reference":{"__symbol":33,"members":[]}}},"useClass":{"reference":{"__symbol":34,"members":[]},"diDeps":[],"lifecycleHooks":[]},"useFactory":null,"deps":[],"multi":false},"module":{"reference":{"__symbol":27,"members":[]},"diDeps":[],"lifecycleHooks":[]}},{"provider":{"token":{"identifier":{"reference":{"__symbol":35,"members":[]}}},"useClass":{"reference":{"__symbol":36,"members":[]},"diDeps":[],"lifecycleHooks":[]},"useFactory":null,"deps":[],"multi":false},"module":{"reference":{"__symbol":27,"members":[]},"diDeps":[],"lifecycleHooks":[]}},{"provider":{"token":{"identifier":{"reference":{"__symbol":37,"members":[]}}},"useClass":{"reference":{"__symbol":38,"members":[]},"diDeps":[],"lifecycleHooks":[]},"useFactory":null,"deps":[],"multi":false},"module":{"reference":{"__symbol":27,"members":[]},"diDeps":[],"lifecycleHooks":[]}},{"provider":{"token":{"identifier":{"reference":{"__symbol":39,"members":[]},"diDeps":[],"lifecycleHooks":[]}},"useClass":{"reference":{"__symbol":39,"members":[]},"diDeps":[],"lifecycleHooks":[]},"useFactory":null,"deps":[],"multi":false},"module":{"reference":{"__symbol":27,"members":[]},"diDeps":[],"lifecycleHooks":[]}},{"provider":{"token":{"identifier":{"reference":{"__symbol":40,"members":[]},"diDeps":[],"lifecycleHooks":[]}},"useClass":{"reference":{"__symbol":40,"members":[]},"diDeps":[],"lifecycleHooks":[]},"useFactory":null,"deps":[],"multi":false},"module":{"reference":{"__symbol":27,"members":[]},"diDeps":[],"lifecycleHooks":[]}},{"provider":{"token":{"identifier":{"reference":{"__symbol":21,"members":[]},"diDeps":[{"isAttribute":false,"isHost":false,"isSelf":false,"isSkipSelf":false,"isOptional":false,"token":{"identifier":{"reference":{"__symbol":22,"members":[]}}}},{"isAttribute":false,"isHost":false,"isSelf":false,"isSkipSelf":false,"isOptional":false,"token":{"identifier":{"reference":{"__symbol":23,"members":[]}}}},{"isAttribute":false,"isHost":false,"isSelf":false,"isSkipSelf":false,"isOptional":false,"token":{"identifier":{"reference":{"__symbol":24,"members":[]}}}}],"lifecycleHooks":[]}},"useClass":{"reference":{"__symbol":21,"members":[]},"diDeps":[{"isAttribute":false,"isHost":false,"isSelf":false,"isSkipSelf":false,"isOptional":false,"token":{"identifier":{"reference":{"__symbol":22,"members":[]}}}},{"isAttribute":false,"isHost":false,"isSelf":false,"isSkipSelf":false,"isOptional":false,"token":{"identifier":{"reference":{"__symbol":23,"members":[]}}}},{"isAttribute":false,"isHost":false,"isSelf":false,"isSkipSelf":false,"isOptional":false,"token":{"identifier":{"reference":{"__symbol":24,"members":[]}}}}],"lifecycleHooks":[]},"useFactory":null,"deps":[{"isAttribute":false,"isHost":false,"isSelf":false,"isSkipSelf":false,"isOptional":false,"token":{"identifier":{"reference":{"__symbol":22,"members":[]}}}},{"isAttribute":false,"isHost":false,"isSelf":false,"isSkipSelf":false,"isOptional":false,"token":{"identifier":{"reference":{"__symbol":23,"members":[]}}}},{"isAttribute":false,"isHost":false,"isSelf":false,"isSkipSelf":false,"isOptional":false,"token":{"identifier":{"reference":{"__symbol":24,"members":[]}}}}],"multi":false},"module":{"reference":{"__symbol":27,"members":[]},"diDeps":[],"lifecycleHooks":[]}},{"provider":{"token":{"identifier":{"reference":{"__symbol":24,"members":[]},"diDeps":[{"isAttribute":false,"isHost":false,"isSelf":false,"isSkipSelf":false,"isOptional":false,"token":{"identifier":{"reference":{"__symbol":41,"members":[]}}}},{"isAttribute":false,"isHost":false,"isSelf":false,"isSkipSelf":false,"isOptional":false,"token":{"identifier":{"reference":{"__symbol":23,"members":[]}}}},{"isAttribute":false,"isHost":false,"isSelf":false,"isSkipSelf":false,"isOptional":false,"token":{"identifier":{"reference":{"__symbol":22,"members":[]}}}}],"lifecycleHooks":[]}},"useClass":{"reference":{"__symbol":24,"members":[]},"diDeps":[{"isAttribute":false,"isHost":false,"isSelf":false,"isSkipSelf":false,"isOptional":false,"token":{"identifier":{"reference":{"__symbol":41,"members":[]}}}},{"isAttribute":false,"isHost":false,"isSelf":false,"isSkipSelf":false,"isOptional":false,"token":{"identifier":{"reference":{"__symbol":23,"members":[]}}}},{"isAttribute":false,"isHost":false,"isSelf":false,"isSkipSelf":false,"isOptional":false,"token":{"identifier":{"reference":{"__symbol":22,"members":[]}}}}],"lifecycleHooks":[]},"useFactory":null,"deps":[{"isAttribute":false,"isHost":false,"isSelf":false,"isSkipSelf":false,"isOptional":false,"token":{"identifier":{"reference":{"__symbol":41,"members":[]}}}},{"isAttribute":false,"isHost":false,"isSelf":false,"isSkipSelf":false,"isOptional":false,"token":{"identifier":{"reference":{"__symbol":23,"members":[]}}}},{"isAttribute":false,"isHost":false,"isSelf":false,"isSkipSelf":false,"isOptional":false,"token":{"identifier":{"reference":{"__symbol":22,"members":[]}}}}],"multi":false},"module":{"reference":{"__symbol":27,"members":[]},"diDeps":[],"lifecycleHooks":[]}},{"provider":{"token":{"identifier":{"reference":{"__symbol":42,"members":[]},"diDeps":[],"lifecycleHooks":[]}},"useClass":{"reference":{"__symbol":42,"members":[]},"diDeps":[],"lifecycleHooks":[]},"useFactory":null,"deps":[],"multi":false},"module":{"reference":{"__symbol":27,"members":[]},"diDeps":[],"lifecycleHooks":[]}},{"provider":{"token":{"identifier":{"reference":{"__symbol":43,"members":[]},"diDeps":[],"lifecycleHooks":[]}},"useClass":{"reference":{"__symbol":43,"members":[]},"diDeps":[],"lifecycleHooks":[]},"useFactory":null,"deps":[],"multi":false},"module":{"reference":{"__symbol":27,"members":[]},"diDeps":[],"lifecycleHooks":[]}},{"provider":{"token":{"identifier":{"reference":{"__symbol":28,"members":[]},"diDeps":[],"lifecycleHooks":[]}},"useClass":{"reference":{"__symbol":28,"members":[]},"diDeps":[],"lifecycleHooks":[]},"useFactory":null,"deps":[],"multi":false},"module":{"reference":{"__symbol":27,"members":[]},"diDeps":[],"lifecycleHooks":[]}},{"provider":{"token":{"identifier":{"reference":{"__symbol":44,"members":[]},"diDeps":[],"lifecycleHooks":[]}},"useClass":{"reference":{"__symbol":44,"members":[]},"diDeps":[],"lifecycleHooks":[]},"useFactory":null,"deps":[],"multi":false},"module":{"reference":{"__symbol":27,"members":[]},"diDeps":[],"lifecycleHooks":[]}},{"provider":{"token":{"identifier":{"reference":{"__symbol":45,"members":[]},"diDeps":[],"lifecycleHooks":[]}},"useClass":{"reference":{"__symbol":45,"members":[]},"diDeps":[],"lifecycleHooks":[]},"useFactory":null,"deps":[],"multi":false},"module":{"reference":{"__symbol":27,"members":[]},"diDeps":[],"lifecycleHooks":[]}},{"provider":{"token":{"identifier":{"reference":{"__symbol":46,"members":[]},"diDeps":[],"lifecycleHooks":[]}},"useClass":{"reference":{"__symbol":46,"members":[]},"diDeps":[],"lifecycleHooks":[]},"useFactory":null,"deps":[],"multi":false},"module":{"reference":{"__symbol":27,"members":[]},"diDeps":[],"lifecycleHooks":[]}},{"provider":{"token":{"identifier":{"reference":{"__symbol":29,"members":[]},"diDeps":[],"lifecycleHooks":[]}},"useClass":{"reference":{"__symbol":29,"members":[]},"diDeps":[],"lifecycleHooks":[]},"useFactory":null,"deps":[],"multi":false},"module":{"reference":{"__symbol":27,"members":[]},"diDeps":[],"lifecycleHooks":[]}},{"provider":{"token":{"identifier":{"reference":{"__symbol":47,"members":[]}}},"useClass":null,"useFactory":{"reference":{"__symbol":48,"members":[]},"diDeps":[{"isAttribute":false,"isHost":false,"isSelf":false,"isSkipSelf":false,"isOptional":false,"token":{"identifier":{"reference":{"__symbol":49,"members":[]}}}},{"isAttribute":false,"isHost":false,"isSelf":false,"isSkipSelf":false,"isOptional":false,"token":{"identifier":{"reference":{"__symbol":50,"members":[]}}}}]},"deps":[{"isAttribute":false,"isHost":false,"isSelf":false,"isSkipSelf":false,"isOptional":false,"token":{"identifier":{"reference":{"__symbol":49,"members":[]}}}},{"isAttribute":false,"isHost":false,"isSelf":false,"isSkipSelf":false,"isOptional":false,"token":{"identifier":{"reference":{"__symbol":50,"members":[]}}}}],"multi":false},"module":{"reference":{"__symbol":51,"members":[]},"diDeps":[],"lifecycleHooks":[]}},{"provider":{"token":{"identifier":{"reference":{"__symbol":52,"members":[]},"diDeps":[],"lifecycleHooks":[]}},"useClass":{"reference":{"__symbol":52,"members":[]},"diDeps":[],"lifecycleHooks":[]},"useFactory":null,"deps":[],"multi":false},"module":{"reference":{"__symbol":51,"members":[]},"diDeps":[],"lifecycleHooks":[]}},{"provider":{"token":{"identifier":{"reference":{"__symbol":50,"members":[]}}},"useClass":{"reference":{"__symbol":53,"members":[]},"diDeps":[],"lifecycleHooks":[]},"useFactory":null,"deps":[],"multi":false},"module":{"reference":{"__symbol":51,"members":[]},"diDeps":[],"lifecycleHooks":[]}},{"provider":{"token":{"identifier":{"reference":{"__symbol":54,"members":[]}}},"useClass":{"reference":{"__symbol":55,"members":[]},"diDeps":[],"lifecycleHooks":[]},"useFactory":null,"deps":[],"multi":false},"module":{"reference":{"__symbol":51,"members":[]},"diDeps":[],"lifecycleHooks":[]}},{"provider":{"token":{"identifier":{"reference":{"__symbol":49,"members":[]},"diDeps":[{"isAttribute":false,"isHost":false,"isSelf":false,"isSkipSelf":false,"isOptional":false,"token":{"identifier":{"reference":{"__symbol":52,"members":[]}}}},{"isAttribute":false,"isHost":false,"isSelf":false,"isSkipSelf":false,"isOptional":false,"token":{"identifier":{"reference":{"__symbol":54,"members":[]}}}},{"isAttribute":false,"isHost":false,"isSelf":false,"isSkipSelf":false,"isOptional":false,"token":{"identifier":{"reference":{"__symbol":56,"members":[]}}}}],"lifecycleHooks":[]}},"useClass":{"reference":{"__symbol":49,"members":[]},"diDeps":[{"isAttribute":false,"isHost":false,"isSelf":false,"isSkipSelf":false,"isOptional":false,"token":{"identifier":{"reference":{"__symbol":52,"members":[]}}}},{"isAttribute":false,"isHost":false,"isSelf":false,"isSkipSelf":false,"isOptional":false,"token":{"identifier":{"reference":{"__symbol":54,"members":[]}}}},{"isAttribute":false,"isHost":false,"isSelf":false,"isSkipSelf":false,"isOptional":false,"token":{"identifier":{"reference":{"__symbol":56,"members":[]}}}}],"lifecycleHooks":[]},"useFactory":null,"deps":[{"isAttribute":false,"isHost":false,"isSelf":false,"isSkipSelf":false,"isOptional":false,"token":{"identifier":{"reference":{"__symbol":52,"members":[]}}}},{"isAttribute":false,"isHost":false,"isSelf":false,"isSkipSelf":false,"isOptional":false,"token":{"identifier":{"reference":{"__symbol":54,"members":[]}}}},{"isAttribute":false,"isHost":false,"isSelf":false,"isSkipSelf":false,"isOptional":false,"token":{"identifier":{"reference":{"__symbol":56,"members":[]}}}}],"multi":false},"module":{"reference":{"__symbol":51,"members":[]},"diDeps":[],"lifecycleHooks":[]}},{"provider":{"token":{"identifier":{"reference":{"__symbol":56,"members":[]}}},"useClass":null,"useFactory":{"reference":{"__symbol":57,"members":[]},"diDeps":[]},"deps":[],"multi":false},"module":{"reference":{"__symbol":51,"members":[]},"diDeps":[],"lifecycleHooks":[]}},{"provider":{"token":{"identifier":{"reference":{"__symbol":58,"members":[]}}},"useClass":null,"useFactory":{"reference":{"__symbol":59,"members":[]},"diDeps":[{"isAttribute":false,"isHost":false,"isSelf":false,"isSkipSelf":false,"isOptional":false,"token":{"identifier":{"reference":{"__symbol":47,"members":[]}}}}]},"deps":[{"isAttribute":false,"isHost":false,"isSelf":false,"isSkipSelf":false,"isOptional":false,"token":{"identifier":{"reference":{"__symbol":47,"members":[]}}}}],"multi":false},"module":{"reference":{"__symbol":60,"members":[]},"diDeps":[],"lifecycleHooks":[]}},{"provider":{"token":{"identifier":{"reference":{"__symbol":61,"members":[]}}},"useClass":{"reference":{"__symbol":62,"members":[]},"diDeps":[],"lifecycleHooks":[]},"useFactory":null,"deps":[],"multi":false},"module":{"reference":{"__symbol":60,"members":[]},"diDeps":[],"lifecycleHooks":[]}},{"provider":{"token":{"identifier":{"reference":{"__symbol":63,"members":[]}}},"useClass":null,"useFactory":{"reference":{"__symbol":64,"members":[]},"diDeps":[{"isAttribute":false,"isHost":false,"isSelf":false,"isSkipSelf":false,"isOptional":false,"token":{"identifier":{"reference":{"__symbol":65,"members":[]}}}}]},"deps":[{"isAttribute":false,"isHost":false,"isSelf":false,"isSkipSelf":false,"isOptional":false,"token":{"identifier":{"reference":{"__symbol":65,"members":[]}}}}],"multi":false},"module":{"reference":{"__symbol":60,"members":[]},"diDeps":[],"lifecycleHooks":[]}},{"provider":{"token":{"identifier":{"reference":{"__symbol":66,"members":[]},"diDeps":[],"lifecycleHooks":[]}},"useClass":{"reference":{"__symbol":66,"members":[]},"diDeps":[],"lifecycleHooks":[]},"useFactory":null,"deps":[],"multi":false},"module":{"reference":{"__symbol":60,"members":[]},"diDeps":[],"lifecycleHooks":[]}},{"provider":{"token":{"identifier":{"reference":{"__symbol":67,"members":[]}}},"useClass":null,"useFactory":null,"multi":false},"module":{"reference":{"__symbol":60,"members":[]},"diDeps":[],"lifecycleHooks":[]}},{"provider":{"token":{"identifier":{"reference":{"__symbol":68,"members":[]},"diDeps":[{"isAttribute":false,"isHost":false,"isSelf":false,"isSkipSelf":false,"isOptional":false,"token":{"identifier":{"reference":{"__symbol":66,"members":[]}}}},{"isAttribute":false,"isHost":false,"isSelf":false,"isSkipSelf":false,"isOptional":false,"token":{"identifier":{"reference":{"__symbol":58,"members":[]}}}},{"isAttribute":false,"isHost":false,"isSelf":false,"isSkipSelf":false,"isOptional":false,"token":{"identifier":{"reference":{"__symbol":61,"members":[]}}}},{"isAttribute":false,"isHost":false,"isSelf":false,"isSkipSelf":false,"isOptional":false,"token":{"identifier":{"reference":{"__symbol":63,"members":[]}}}},{"isAttribute":false,"isHost":false,"isSelf":false,"isSkipSelf":false,"isOptional":false,"token":{"identifier":{"reference":{"__symbol":67,"members":[]}}}}],"lifecycleHooks":[]}},"useClass":{"reference":{"__symbol":68,"members":[]},"diDeps":[{"isAttribute":false,"isHost":false,"isSelf":false,"isSkipSelf":false,"isOptional":false,"token":{"identifier":{"reference":{"__symbol":66,"members":[]}}}},{"isAttribute":false,"isHost":false,"isSelf":false,"isSkipSelf":false,"isOptional":false,"token":{"identifier":{"reference":{"__symbol":58,"members":[]}}}},{"isAttribute":false,"isHost":false,"isSelf":false,"isSkipSelf":false,"isOptional":false,"token":{"identifier":{"reference":{"__symbol":61,"members":[]}}}},{"isAttribute":false,"isHost":false,"isSelf":false,"isSkipSelf":false,"isOptional":false,"token":{"identifier":{"reference":{"__symbol":63,"members":[]}}}},{"isAttribute":false,"isHost":false,"isSelf":false,"isSkipSelf":false,"isOptional":false,"token":{"identifier":{"reference":{"__symbol":67,"members":[]}}}}],"lifecycleHooks":[]},"useFactory":null,"deps":[{"isAttribute":false,"isHost":false,"isSelf":false,"isSkipSelf":false,"isOptional":false,"token":{"identifier":{"reference":{"__symbol":66,"members":[]}}}},{"isAttribute":false,"isHost":false,"isSelf":false,"isSkipSelf":false,"isOptional":false,"token":{"identifier":{"reference":{"__symbol":58,"members":[]}}}},{"isAttribute":false,"isHost":false,"isSelf":false,"isSkipSelf":false,"isOptional":false,"token":{"identifier":{"reference":{"__symbol":61,"members":[]}}}},{"isAttribute":false,"isHost":false,"isSelf":false,"isSkipSelf":false,"isOptional":false,"token":{"identifier":{"reference":{"__symbol":63,"members":[]}}}},{"isAttribute":false,"isHost":false,"isSelf":false,"isSkipSelf":false,"isOptional":false,"token":{"identifier":{"reference":{"__symbol":67,"members":[]}}}}],"multi":false},"module":{"reference":{"__symbol":60,"members":[]},"diDeps":[],"lifecycleHooks":[]}},{"provider":{"token":{"identifier":{"reference":{"__symbol":69,"members":[]},"diDeps":[],"lifecycleHooks":[]}},"useClass":{"reference":{"__symbol":69,"members":[]},"diDeps":[],"lifecycleHooks":[]},"useFactory":null,"deps":[],"multi":false},"module":{"reference":{"__symbol":70,"members":[]},"diDeps":[],"lifecycleHooks":[]}},{"provider":{"token":{"identifier":{"reference":{"__symbol":71,"members":[]},"diDeps":[{"isAttribute":false,"isHost":false,"isSelf":false,"isSkipSelf":false,"isOptional":false,"token":{"identifier":{"reference":{"__symbol":69,"members":[]}}}}],"lifecycleHooks":[]}},"useClass":{"reference":{"__symbol":71,"members":[]},"diDeps":[{"isAttribute":false,"isHost":false,"isSelf":false,"isSkipSelf":false,"isOptional":false,"token":{"identifier":{"reference":{"__symbol":69,"members":[]}}}}],"lifecycleHooks":[]},"useFactory":null,"deps":[{"isAttribute":false,"isHost":false,"isSelf":false,"isSkipSelf":false,"isOptional":false,"token":{"identifier":{"reference":{"__symbol":69,"members":[]}}}}],"multi":false},"module":{"reference":{"__symbol":70,"members":[]},"diDeps":[],"lifecycleHooks":[]}},{"provider":{"token":{"identifier":{"reference":{"__symbol":72,"members":[]},"diDeps":[],"lifecycleHooks":[]}},"useClass":{"reference":{"__symbol":72,"members":[]},"diDeps":[],"lifecycleHooks":[]},"useFactory":null,"deps":[],"multi":false},"module":{"reference":{"__symbol":70,"members":[]},"diDeps":[],"lifecycleHooks":[]}},{"provider":{"token":{"identifier":{"reference":{"__symbol":73,"members":[]},"diDeps":[],"lifecycleHooks":[]}},"useClass":{"reference":{"__symbol":73,"members":[]},"diDeps":[],"lifecycleHooks":[]},"useFactory":null,"deps":[],"multi":false},"module":{"reference":{"__symbol":70,"members":[]},"diDeps":[],"lifecycleHooks":[]}},{"provider":{"token":{"identifier":{"reference":{"__symbol":74,"members":[]},"diDeps":[{"isAttribute":false,"isHost":false,"isSelf":false,"isSkipSelf":false,"isOptional":false,"token":{"identifier":{"reference":{"__symbol":75,"members":[]}}}},{"isAttribute":false,"isHost":false,"isSelf":false,"isSkipSelf":false,"isOptional":false,"token":{"identifier":{"reference":{"__symbol":23,"members":[]}}}}],"lifecycleHooks":[]}},"useClass":{"reference":{"__symbol":74,"members":[]},"diDeps":[{"isAttribute":false,"isHost":false,"isSelf":false,"isSkipSelf":false,"isOptional":false,"token":{"identifier":{"reference":{"__symbol":75,"members":[]}}}},{"isAttribute":false,"isHost":false,"isSelf":false,"isSkipSelf":false,"isOptional":false,"token":{"identifier":{"reference":{"__symbol":23,"members":[]}}}}],"lifecycleHooks":[]},"useFactory":null,"deps":[{"isAttribute":false,"isHost":false,"isSelf":false,"isSkipSelf":false,"isOptional":false,"token":{"identifier":{"reference":{"__symbol":75,"members":[]}}}},{"isAttribute":false,"isHost":false,"isSelf":false,"isSkipSelf":false,"isOptional":false,"token":{"identifier":{"reference":{"__symbol":23,"members":[]}}}}],"multi":false},"module":{"reference":{"__symbol":76,"members":[]},"diDeps":[],"lifecycleHooks":[]}},{"provider":{"token":{"identifier":{"reference":{"__symbol":77,"members":[]},"diDeps":[],"lifecycleHooks":[]}},"useClass":{"reference":{"__symbol":77,"members":[]},"diDeps":[],"lifecycleHooks":[]},"useFactory":null,"deps":[],"multi":false},"module":{"reference":{"__symbol":0,"members":[]},"diDeps":[],"lifecycleHooks":[]}},{"provider":{"token":{"identifier":{"reference":{"__symbol":78,"members":[]},"diDeps":[{"isAttribute":false,"isHost":false,"isSelf":false,"isSkipSelf":false,"isOptional":false,"token":{"identifier":{"reference":{"__symbol":79,"members":[]}}}}],"lifecycleHooks":[]}},"useClass":{"reference":{"__symbol":78,"members":[]},"diDeps":[{"isAttribute":false,"isHost":false,"isSelf":false,"isSkipSelf":false,"isOptional":false,"token":{"identifier":{"reference":{"__symbol":79,"members":[]}}}}],"lifecycleHooks":[]},"useFactory":null,"deps":[{"isAttribute":false,"isHost":false,"isSelf":false,"isSkipSelf":false,"isOptional":false,"token":{"identifier":{"reference":{"__symbol":79,"members":[]}}}}],"multi":false},"module":{"reference":{"__symbol":0,"members":[]},"diDeps":[],"lifecycleHooks":[]}},{"provider":{"token":{"identifier":{"reference":{"__symbol":80,"members":[]},"diDeps":[],"lifecycleHooks":[]}},"useClass":{"reference":{"__symbol":80,"members":[]},"diDeps":[],"lifecycleHooks":[]},"useFactory":null,"deps":[],"multi":false},"module":{"reference":{"__symbol":0,"members":[]},"diDeps":[],"lifecycleHooks":[]}},{"provider":{"token":{"identifier":{"reference":{"__symbol":81,"members":[]},"diDeps":[],"lifecycleHooks":[]}},"useClass":{"reference":{"__symbol":81,"members":[]},"diDeps":[],"lifecycleHooks":[]},"useFactory":null,"deps":[],"multi":false},"module":{"reference":{"__symbol":0,"members":[]},"diDeps":[],"lifecycleHooks":[]}},{"provider":{"token":{"identifier":{"reference":{"__symbol":82,"members":[]},"diDeps":[],"lifecycleHooks":[]}},"useClass":{"reference":{"__symbol":82,"members":[]},"diDeps":[],"lifecycleHooks":[]},"useFactory":null,"deps":[],"multi":false},"module":{"reference":{"__symbol":0,"members":[]},"diDeps":[],"lifecycleHooks":[]}},{"provider":{"token":{"identifier":{"reference":{"__symbol":83,"members":[]},"diDeps":[],"lifecycleHooks":[]}},"useClass":{"reference":{"__symbol":83,"members":[]},"diDeps":[],"lifecycleHooks":[]},"useFactory":null,"deps":[],"multi":false},"module":{"reference":{"__symbol":0,"members":[]},"diDeps":[],"lifecycleHooks":[]}},{"provider":{"token":{"identifier":{"reference":{"__symbol":84,"members":[]},"diDeps":[{"isAttribute":false,"isHost":false,"isSelf":false,"isSkipSelf":false,"isOptional":false,"token":{"identifier":{"reference":{"__symbol":85,"members":[]}}}},{"isAttribute":false,"isHost":false,"isSelf":false,"isSkipSelf":false,"isOptional":false,"token":{"identifier":{"reference":{"__symbol":65,"members":[]}}}},{"isAttribute":false,"isHost":false,"isSelf":false,"isSkipSelf":false,"isOptional":false,"token":{"identifier":{"reference":{"__symbol":68,"members":[]}}}}],"lifecycleHooks":[]}},"useClass":{"reference":{"__symbol":84,"members":[]},"diDeps":[{"isAttribute":false,"isHost":false,"isSelf":false,"isSkipSelf":false,"isOptional":false,"token":{"identifier":{"reference":{"__symbol":85,"members":[]}}}},{"isAttribute":false,"isHost":false,"isSelf":false,"isSkipSelf":false,"isOptional":false,"token":{"identifier":{"reference":{"__symbol":65,"members":[]}}}},{"isAttribute":false,"isHost":false,"isSelf":false,"isSkipSelf":false,"isOptional":false,"token":{"identifier":{"reference":{"__symbol":68,"members":[]}}}}],"lifecycleHooks":[]},"useFactory":null,"deps":[{"isAttribute":false,"isHost":false,"isSelf":false,"isSkipSelf":false,"isOptional":false,"token":{"identifier":{"reference":{"__symbol":85,"members":[]}}}},{"isAttribute":false,"isHost":false,"isSelf":false,"isSkipSelf":false,"isOptional":false,"token":{"identifier":{"reference":{"__symbol":65,"members":[]}}}},{"isAttribute":false,"isHost":false,"isSelf":false,"isSkipSelf":false,"isOptional":false,"token":{"identifier":{"reference":{"__symbol":68,"members":[]}}}}],"multi":false},"module":{"reference":{"__symbol":0,"members":[]},"diDeps":[],"lifecycleHooks":[]}},{"provider":{"token":{"identifier":{"reference":{"__symbol":86,"members":[]},"diDeps":[{"isAttribute":false,"isHost":false,"isSelf":false,"isSkipSelf":false,"isOptional":false,"token":{"identifier":{"reference":{"__symbol":68,"members":[]}}}},{"isAttribute":false,"isHost":false,"isSelf":false,"isSkipSelf":false,"isOptional":false,"token":{"identifier":{"reference":{"__symbol":65,"members":[]}}}}],"lifecycleHooks":[]}},"useClass":{"reference":{"__symbol":86,"members":[]},"diDeps":[{"isAttribute":false,"isHost":false,"isSelf":false,"isSkipSelf":false,"isOptional":false,"token":{"identifier":{"reference":{"__symbol":68,"members":[]}}}},{"isAttribute":false,"isHost":false,"isSelf":false,"isSkipSelf":false,"isOptional":false,"token":{"identifier":{"reference":{"__symbol":65,"members":[]}}}}],"lifecycleHooks":[]},"useFactory":null,"deps":[{"isAttribute":false,"isHost":false,"isSelf":false,"isSkipSelf":false,"isOptional":false,"token":{"identifier":{"reference":{"__symbol":68,"members":[]}}}},{"isAttribute":false,"isHost":false,"isSelf":false,"isSkipSelf":false,"isOptional":false,"token":{"identifier":{"reference":{"__symbol":65,"members":[]}}}}],"multi":false},"module":{"reference":{"__symbol":0,"members":[]},"diDeps":[],"lifecycleHooks":[]}},{"provider":{"token":{"identifier":{"reference":{"__symbol":87,"members":[]}}},"useClass":null,"useValue":{"alertAsToast":false,"i18nEnabled":true,"defaultI18nLang":"en"},"useFactory":null,"multi":false},"module":{"reference":{"__symbol":0,"members":[]},"diDeps":[],"lifecycleHooks":[]}},{"provider":{"token":{"identifier":{"reference":{"__symbol":65,"members":[]},"diDeps":[{"isAttribute":false,"isHost":false,"isSelf":false,"isSkipSelf":false,"isOptional":false,"token":{"identifier":{"reference":{"__symbol":87,"members":[]}}}}],"lifecycleHooks":[]}},"useClass":{"reference":{"__symbol":65,"members":[]},"diDeps":[{"isAttribute":false,"isHost":false,"isSelf":false,"isSkipSelf":false,"isOptional":false,"token":{"identifier":{"reference":{"__symbol":87,"members":[]}}}}],"lifecycleHooks":[]},"useFactory":null,"deps":[{"isAttribute":false,"isHost":false,"isSelf":false,"isSkipSelf":false,"isOptional":false,"token":{"identifier":{"reference":{"__symbol":87,"members":[]}}}}],"multi":false},"module":{"reference":{"__symbol":0,"members":[]},"diDeps":[],"lifecycleHooks":[]}},{"provider":{"token":{"identifier":{"reference":{"__symbol":75,"members":[]}}},"useClass":null,"useValue":{},"useFactory":null,"multi":false},"module":{"reference":{"__symbol":0,"members":[]},"diDeps":[],"lifecycleHooks":[]}},{"provider":{"token":{"identifier":{"reference":{"__symbol":88,"members":[]}}},"useClass":null,"useFactory":{"reference":{"__symbol":89,"members":[]},"diDeps":[{"isAttribute":false,"isHost":false,"isSelf":false,"isSkipSelf":false,"isOptional":false,"token":{"identifier":{"reference":{"__symbol":74,"members":[]}}}}]},"deps":[{"isAttribute":false,"isHost":false,"isSelf":false,"isSkipSelf":false,"isOptional":false,"token":{"identifier":{"reference":{"__symbol":74,"members":[]}}}}],"multi":false},"module":{"reference":{"__symbol":0,"members":[]},"diDeps":[],"lifecycleHooks":[]}}],"modules":[{"reference":{"__symbol":18,"members":[]},"diDeps":[],"lifecycleHooks":[]},{"reference":{"__symbol":90,"members":[]},"diDeps":[],"lifecycleHooks":[]},{"reference":{"__symbol":91,"members":[]},"diDeps":[],"lifecycleHooks":[]},{"reference":{"__symbol":92,"members":[]},"diDeps":[],"lifecycleHooks":[]},{"reference":{"__symbol":93,"members":[]},"diDeps":[],"lifecycleHooks":[]},{"reference":{"__symbol":94,"members":[]},"diDeps":[],"lifecycleHooks":[]},{"reference":{"__symbol":95,"members":[]},"diDeps":[],"lifecycleHooks":[]},{"reference":{"__symbol":96,"members":[]},"diDeps":[],"lifecycleHooks":[]},{"reference":{"__symbol":97,"members":[]},"diDeps":[],"lifecycleHooks":[]},{"reference":{"__symbol":98,"members":[]},"diDeps":[],"lifecycleHooks":[]},{"reference":{"__symbol":20,"members":[]},"diDeps":[],"lifecycleHooks":[]},{"reference":{"__symbol":99,"members":[]},"diDeps":[],"lifecycleHooks":[]},{"reference":{"__symbol":100,"members":[]},"diDeps":[],"lifecycleHooks":[]},{"reference":{"__symbol":25,"members":[]},"diDeps":[],"lifecycleHooks":[]},{"reference":{"__symbol":101,"members":[]},"diDeps":[],"lifecycleHooks":[]},{"reference":{"__symbol":102,"members":[]},"diDeps":[],"lifecycleHooks":[]},{"reference":{"__symbol":103,"members":[]},"diDeps":[],"lifecycleHooks":[]},{"reference":{"__symbol":104,"members":[]},"diDeps":[],"lifecycleHooks":[]},{"reference":{"__symbol":105,"members":[]},"diDeps":[],"lifecycleHooks":[]},{"reference":{"__symbol":27,"members":[]},"diDeps":[],"lifecycleHooks":[]},{"reference":{"__symbol":106,"members":[]},"diDeps":[],"lifecycleHooks":[]},{"reference":{"__symbol":51,"members":[]},"diDeps":[],"lifecycleHooks":[]},{"reference":{"__symbol":60,"members":[]},"diDeps":[],"lifecycleHooks":[]},{"reference":{"__symbol":70,"members":[]},"diDeps":[],"lifecycleHooks":[]},{"reference":{"__symbol":76,"members":[]},"diDeps":[],"lifecycleHooks":[]},{"reference":{"__symbol":107,"members":[]},"diDeps":[],"lifecycleHooks":[]},{"reference":{"__symbol":0,"members":[]},"diDeps":[],"lifecycleHooks":[]}],"exportedDirectives":[{"reference":{"__symbol":108,"members":[]}},{"reference":{"__symbol":109,"members":[]}},{"reference":{"__symbol":110,"members":[]}},{"reference":{"__symbol":111,"members":[]}},{"reference":{"__symbol":112,"members":[]}},{"reference":{"__symbol":113,"members":[]}},{"reference":{"__symbol":114,"members":[]}},{"reference":{"__symbol":115,"members":[]}},{"reference":{"__symbol":116,"members":[]}},{"reference":{"__symbol":117,"members":[]}},{"reference":{"__symbol":118,"members":[]}},{"reference":{"__symbol":119,"members":[]}},{"reference":{"__symbol":120,"members":[]}},{"reference":{"__symbol":121,"members":[]}},{"reference":{"__symbol":122,"members":[]}},{"reference":{"__symbol":123,"members":[]}},{"reference":{"__symbol":124,"members":[]}},{"reference":{"__symbol":125,"members":[]}},{"reference":{"__symbol":126,"members":[]}},{"reference":{"__symbol":127,"members":[]}},{"reference":{"__symbol":128,"members":[]}},{"reference":{"__symbol":129,"members":[]}},{"reference":{"__symbol":130,"members":[]}},{"reference":{"__symbol":131,"members":[]}},{"reference":{"__symbol":132,"members":[]}},{"reference":{"__symbol":133,"members":[]}},{"reference":{"__symbol":134,"members":[]}},{"reference":{"__symbol":135,"members":[]}},{"reference":{"__symbol":136,"members":[]}},{"reference":{"__symbol":137,"members":[]}},{"reference":{"__symbol":138,"members":[]}},{"reference":{"__symbol":139,"members":[]}},{"reference":{"__symbol":140,"members":[]}},{"reference":{"__symbol":141,"members":[]}},{"reference":{"__symbol":142,"members":[]}},{"reference":{"__symbol":143,"members":[]}},{"reference":{"__symbol":1,"members":[]}},{"reference":{"__symbol":144,"members":[]}},{"reference":{"__symbol":145,"members":[]}},{"reference":{"__symbol":146,"members":[]}},{"reference":{"__symbol":147,"members":[]}},{"reference":{"__symbol":148,"members":[]}},{"reference":{"__symbol":149,"members":[]}},{"reference":{"__symbol":7,"members":[]}},{"reference":{"__symbol":150,"members":[]}},{"reference":{"__symbol":151,"members":[]}},{"reference":{"__symbol":152,"members":[]}},{"reference":{"__symbol":153,"members":[]}},{"reference":{"__symbol":154,"members":[]}},{"reference":{"__symbol":155,"members":[]}},{"reference":{"__symbol":156,"members":[]}},{"reference":{"__symbol":157,"members":[]}},{"reference":{"__symbol":158,"members":[]}},{"reference":{"__symbol":159,"members":[]}},{"reference":{"__symbol":160,"members":[]}},{"reference":{"__symbol":161,"members":[]}},{"reference":{"__symbol":162,"members":[]}},{"reference":{"__symbol":163,"members":[]}},{"reference":{"__symbol":164,"members":[]}},{"reference":{"__symbol":165,"members":[]}},{"reference":{"__symbol":166,"members":[]}},{"reference":{"__symbol":167,"members":[]}},{"reference":{"__symbol":168,"members":[]}},{"reference":{"__symbol":169,"members":[]}},{"reference":{"__symbol":170,"members":[]}},{"reference":{"__symbol":171,"members":[]}}],"exportedPipes":[{"reference":{"__symbol":172,"members":[]}},{"reference":{"__symbol":173,"members":[]}},{"reference":{"__symbol":174,"members":[]}},{"reference":{"__symbol":175,"members":[]}},{"reference":{"__symbol":176,"members":[]}},{"reference":{"__symbol":177,"members":[]}},{"reference":{"__symbol":178,"members":[]}},{"reference":{"__symbol":179,"members":[]}},{"reference":{"__symbol":180,"members":[]}},{"reference":{"__symbol":79,"members":[]}},{"reference":{"__symbol":181,"members":[]}},{"reference":{"__symbol":182,"members":[]}},{"reference":{"__symbol":183,"members":[]}},{"reference":{"__symbol":184,"members":[]}},{"reference":{"__symbol":185,"members":[]}},{"reference":{"__symbol":186,"members":[]}},{"reference":{"__symbol":187,"members":[]}},{"reference":{"__symbol":188,"members":[]}},{"reference":{"__symbol":189,"members":[]}},{"reference":{"__symbol":190,"members":[]}}]}}],"symbols":[{"__symbol":0,"name":"NeojhipsterSharedLibsModule","filePath":"/Users/milandeket/work/upwork/src/main/webapp/app/shared/shared-libs.module.d.ts"},{"__symbol":1,"name":"NgbAlert","filePath":"/Users/milandeket/work/upwork/node_modules/@ng-bootstrap/ng-bootstrap/alert/alert.d.ts"},{"__symbol":2,"name":"NgbAlertNgFactory","filePath":"/Users/milandeket/work/upwork/node_modules/@ng-bootstrap/ng-bootstrap/alert/alert.ngfactory.d.ts"},{"__symbol":3,"name":"NgbTooltipWindow","filePath":"/Users/milandeket/work/upwork/node_modules/@ng-bootstrap/ng-bootstrap/tooltip/tooltip.d.ts"},{"__symbol":4,"name":"NgbTooltipWindowNgFactory","filePath":"/Users/milandeket/work/upwork/node_modules/@ng-bootstrap/ng-bootstrap/tooltip/tooltip.ngfactory.d.ts"},{"__symbol":5,"name":"NgbTypeaheadWindow","filePath":"/Users/milandeket/work/upwork/node_modules/@ng-bootstrap/ng-bootstrap/typeahead/typeahead-window.d.ts"},{"__symbol":6,"name":"NgbTypeaheadWindowNgFactory","filePath":"/Users/milandeket/work/upwork/node_modules/@ng-bootstrap/ng-bootstrap/typeahead/typeahead-window.ngfactory.d.ts"},{"__symbol":7,"name":"NgbDatepicker","filePath":"/Users/milandeket/work/upwork/node_modules/@ng-bootstrap/ng-bootstrap/datepicker/datepicker.d.ts"},{"__symbol":8,"name":"NgbDatepickerNgFactory","filePath":"/Users/milandeket/work/upwork/node_modules/@ng-bootstrap/ng-bootstrap/datepicker/datepicker.ngfactory.d.ts"},{"__symbol":9,"name":"NgbModalBackdrop","filePath":"/Users/milandeket/work/upwork/node_modules/@ng-bootstrap/ng-bootstrap/modal/modal-backdrop.d.ts"},{"__symbol":10,"name":"NgbModalBackdropNgFactory","filePath":"/Users/milandeket/work/upwork/node_modules/@ng-bootstrap/ng-bootstrap/modal/modal-backdrop.ngfactory.d.ts"},{"__symbol":11,"name":"NgbModalWindow","filePath":"/Users/milandeket/work/upwork/node_modules/@ng-bootstrap/ng-bootstrap/modal/modal-window.d.ts"},{"__symbol":12,"name":"NgbModalWindowNgFactory","filePath":"/Users/milandeket/work/upwork/node_modules/@ng-bootstrap/ng-bootstrap/modal/modal-window.ngfactory.d.ts"},{"__symbol":13,"name":"NgbPopoverWindow","filePath":"/Users/milandeket/work/upwork/node_modules/@ng-bootstrap/ng-bootstrap/popover/popover.d.ts"},{"__symbol":14,"name":"NgbPopoverWindowNgFactory","filePath":"/Users/milandeket/work/upwork/node_modules/@ng-bootstrap/ng-bootstrap/popover/popover.ngfactory.d.ts"},{"__symbol":15,"name":"NgLocalization","filePath":"/Users/milandeket/work/upwork/node_modules/@angular/common/common.d.ts"},{"__symbol":16,"name":"NgLocaleLocalization","filePath":"/Users/milandeket/work/upwork/node_modules/@angular/common/common.d.ts"},{"__symbol":17,"name":"LOCALE_ID","filePath":"/Users/milandeket/work/upwork/node_modules/@angular/core/core.d.ts"},{"__symbol":18,"name":"CommonModule","filePath":"/Users/milandeket/work/upwork/node_modules/@angular/common/common.d.ts"},{"__symbol":19,"name":"ɵi","filePath":"/Users/milandeket/work/upwork/node_modules/@angular/forms/forms.d.ts"},{"__symbol":20,"name":"FormsModule","filePath":"/Users/milandeket/work/upwork/node_modules/@angular/forms/forms.d.ts"},{"__symbol":21,"name":"NgbModal","filePath":"/Users/milandeket/work/upwork/node_modules/@ng-bootstrap/ng-bootstrap/modal/modal.d.ts"},{"__symbol":22,"name":"ComponentFactoryResolver","filePath":"/Users/milandeket/work/upwork/node_modules/@angular/core/core.d.ts"},{"__symbol":23,"name":"Injector","filePath":"/Users/milandeket/work/upwork/node_modules/@angular/core/core.d.ts"},{"__symbol":24,"name":"NgbModalStack","filePath":"/Users/milandeket/work/upwork/node_modules/@ng-bootstrap/ng-bootstrap/modal/modal-stack.d.ts"},{"__symbol":25,"name":"NgbModalModule","filePath":"/Users/milandeket/work/upwork/node_modules/@ng-bootstrap/ng-bootstrap/modal/modal.module.d.ts"},{"__symbol":26,"name":"NgbAlertConfig","filePath":"/Users/milandeket/work/upwork/node_modules/@ng-bootstrap/ng-bootstrap/alert/alert-config.d.ts"},{"__symbol":27,"name":"NgbRootModule","filePath":"/Users/milandeket/work/upwork/node_modules/@ng-bootstrap/ng-bootstrap/index.d.ts"},{"__symbol":28,"name":"NgbProgressbarConfig","filePath":"/Users/milandeket/work/upwork/node_modules/@ng-bootstrap/ng-bootstrap/progressbar/progressbar-config.d.ts"},{"__symbol":29,"name":"NgbTooltipConfig","filePath":"/Users/milandeket/work/upwork/node_modules/@ng-bootstrap/ng-bootstrap/tooltip/tooltip-config.d.ts"},{"__symbol":30,"name":"NgbTypeaheadConfig","filePath":"/Users/milandeket/work/upwork/node_modules/@ng-bootstrap/ng-bootstrap/typeahead/typeahead-config.d.ts"},{"__symbol":31,"name":"NgbAccordionConfig","filePath":"/Users/milandeket/work/upwork/node_modules/@ng-bootstrap/ng-bootstrap/accordion/accordion-config.d.ts"},{"__symbol":32,"name":"NgbCarouselConfig","filePath":"/Users/milandeket/work/upwork/node_modules/@ng-bootstrap/ng-bootstrap/carousel/carousel-config.d.ts"},{"__symbol":33,"name":"NgbCalendar","filePath":"/Users/milandeket/work/upwork/node_modules/@ng-bootstrap/ng-bootstrap/datepicker/ngb-calendar.d.ts"},{"__symbol":34,"name":"NgbCalendarGregorian","filePath":"/Users/milandeket/work/upwork/node_modules/@ng-bootstrap/ng-bootstrap/datepicker/ngb-calendar.d.ts"},{"__symbol":35,"name":"NgbDatepickerI18n","filePath":"/Users/milandeket/work/upwork/node_modules/@ng-bootstrap/ng-bootstrap/datepicker/datepicker-i18n.d.ts"},{"__symbol":36,"name":"NgbDatepickerI18nDefault","filePath":"/Users/milandeket/work/upwork/node_modules/@ng-bootstrap/ng-bootstrap/datepicker/datepicker-i18n.d.ts"},{"__symbol":37,"name":"NgbDateParserFormatter","filePath":"/Users/milandeket/work/upwork/node_modules/@ng-bootstrap/ng-bootstrap/datepicker/ngb-date-parser-formatter.d.ts"},{"__symbol":38,"name":"NgbDateISOParserFormatter","filePath":"/Users/milandeket/work/upwork/node_modules/@ng-bootstrap/ng-bootstrap/datepicker/ngb-date-parser-formatter.d.ts"},{"__symbol":39,"name":"NgbDatepickerConfig","filePath":"/Users/milandeket/work/upwork/node_modules/@ng-bootstrap/ng-bootstrap/datepicker/datepicker-config.d.ts"},{"__symbol":40,"name":"NgbDropdownConfig","filePath":"/Users/milandeket/work/upwork/node_modules/@ng-bootstrap/ng-bootstrap/dropdown/dropdown-config.d.ts"},{"__symbol":41,"name":"ApplicationRef","filePath":"/Users/milandeket/work/upwork/node_modules/@angular/core/core.d.ts"},{"__symbol":42,"name":"NgbPaginationConfig","filePath":"/Users/milandeket/work/upwork/node_modules/@ng-bootstrap/ng-bootstrap/pagination/pagination-config.d.ts"},{"__symbol":43,"name":"NgbPopoverConfig","filePath":"/Users/milandeket/work/upwork/node_modules/@ng-bootstrap/ng-bootstrap/popover/popover-config.d.ts"},{"__symbol":44,"name":"NgbRatingConfig","filePath":"/Users/milandeket/work/upwork/node_modules/@ng-bootstrap/ng-bootstrap/rating/rating-config.d.ts"},{"__symbol":45,"name":"NgbTabsetConfig","filePath":"/Users/milandeket/work/upwork/node_modules/@ng-bootstrap/ng-bootstrap/tabset/tabset-config.d.ts"},{"__symbol":46,"name":"NgbTimepickerConfig","filePath":"/Users/milandeket/work/upwork/node_modules/@ng-bootstrap/ng-bootstrap/timepicker/timepicker-config.d.ts"},{"__symbol":47,"name":"Http","filePath":"/Users/milandeket/work/upwork/node_modules/@angular/http/http.d.ts"},{"__symbol":48,"name":"ɵc","filePath":"/Users/milandeket/work/upwork/node_modules/@angular/http/http.d.ts"},{"__symbol":49,"name":"XHRBackend","filePath":"/Users/milandeket/work/upwork/node_modules/@angular/http/http.d.ts"},{"__symbol":50,"name":"RequestOptions","filePath":"/Users/milandeket/work/upwork/node_modules/@angular/http/http.d.ts"},{"__symbol":51,"name":"HttpModule","filePath":"/Users/milandeket/work/upwork/node_modules/@angular/http/http.d.ts"},{"__symbol":52,"name":"BrowserXhr","filePath":"/Users/milandeket/work/upwork/node_modules/@angular/http/http.d.ts"},{"__symbol":53,"name":"BaseRequestOptions","filePath":"/Users/milandeket/work/upwork/node_modules/@angular/http/http.d.ts"},{"__symbol":54,"name":"ResponseOptions","filePath":"/Users/milandeket/work/upwork/node_modules/@angular/http/http.d.ts"},{"__symbol":55,"name":"BaseResponseOptions","filePath":"/Users/milandeket/work/upwork/node_modules/@angular/http/http.d.ts"},{"__symbol":56,"name":"XSRFStrategy","filePath":"/Users/milandeket/work/upwork/node_modules/@angular/http/http.d.ts"},{"__symbol":57,"name":"ɵb","filePath":"/Users/milandeket/work/upwork/node_modules/@angular/http/http.d.ts"},{"__symbol":58,"name":"TranslateLoader","filePath":"/Users/milandeket/work/upwork/node_modules/@ngx-translate/core/src/translate.loader.d.ts"},{"__symbol":59,"name":"translatePartialLoader","filePath":"/Users/milandeket/work/upwork/node_modules/ng-jhipster/index.d.ts"},{"__symbol":60,"name":"NgJhipsterModule","filePath":"/Users/milandeket/work/upwork/node_modules/ng-jhipster/index.d.ts"},{"__symbol":61,"name":"TranslateParser","filePath":"/Users/milandeket/work/upwork/node_modules/@ngx-translate/core/src/translate.parser.d.ts"},{"__symbol":62,"name":"TranslateDefaultParser","filePath":"/Users/milandeket/work/upwork/node_modules/@ngx-translate/core/src/translate.parser.d.ts"},{"__symbol":63,"name":"MissingTranslationHandler","filePath":"/Users/milandeket/work/upwork/node_modules/@ngx-translate/core/src/missing-translation-handler.d.ts"},{"__symbol":64,"name":"missingTranslationHandler","filePath":"/Users/milandeket/work/upwork/node_modules/ng-jhipster/index.d.ts"},{"__symbol":65,"name":"JhiConfigService","filePath":"/Users/milandeket/work/upwork/node_modules/ng-jhipster/src/config.service.d.ts"},{"__symbol":66,"name":"TranslateStore","filePath":"/Users/milandeket/work/upwork/node_modules/@ngx-translate/core/src/translate.store.d.ts"},{"__symbol":67,"name":"USE_STORE","filePath":"/Users/milandeket/work/upwork/node_modules/@ngx-translate/core/src/translate.service.d.ts"},{"__symbol":68,"name":"TranslateService","filePath":"/Users/milandeket/work/upwork/node_modules/@ngx-translate/core/src/translate.service.d.ts"},{"__symbol":69,"name":"ɵc","filePath":"/Users/milandeket/work/upwork/node_modules/ngx-infinite-scroll/index.d.ts"},{"__symbol":70,"name":"InfiniteScrollModule","filePath":"/Users/milandeket/work/upwork/node_modules/ngx-infinite-scroll/index.d.ts"},{"__symbol":71,"name":"ɵb","filePath":"/Users/milandeket/work/upwork/node_modules/ngx-infinite-scroll/index.d.ts"},{"__symbol":72,"name":"ɵd","filePath":"/Users/milandeket/work/upwork/node_modules/ngx-infinite-scroll/index.d.ts"},{"__symbol":73,"name":"ɵe","filePath":"/Users/milandeket/work/upwork/node_modules/ngx-infinite-scroll/index.d.ts"},{"__symbol":74,"name":"CookieOptionsProvider","filePath":"/Users/milandeket/work/upwork/node_modules/ngx-cookie/src/cookie-options-provider.d.ts"},{"__symbol":75,"name":"COOKIE_OPTIONS","filePath":"/Users/milandeket/work/upwork/node_modules/ngx-cookie/src/cookie-options-provider.d.ts"},{"__symbol":76,"name":"CookieModule","filePath":"/Users/milandeket/work/upwork/node_modules/ngx-cookie/index.d.ts"},{"__symbol":77,"name":"JhiDataUtils","filePath":"/Users/milandeket/work/upwork/node_modules/ng-jhipster/src/service/data-util.service.d.ts"},{"__symbol":78,"name":"JhiDateUtils","filePath":"/Users/milandeket/work/upwork/node_modules/ng-jhipster/src/service/date-util.service.d.ts"},{"__symbol":79,"name":"DatePipe","filePath":"/Users/milandeket/work/upwork/node_modules/@angular/common/common.d.ts"},{"__symbol":80,"name":"JhiEventManager","filePath":"/Users/milandeket/work/upwork/node_modules/ng-jhipster/src/service/event-manager.service.d.ts"},{"__symbol":81,"name":"JhiParseLinks","filePath":"/Users/milandeket/work/upwork/node_modules/ng-jhipster/src/service/parse-links.service.d.ts"},{"__symbol":82,"name":"JhiPaginationUtil","filePath":"/Users/milandeket/work/upwork/node_modules/ng-jhipster/src/service/pagination-util.service.d.ts"},{"__symbol":83,"name":"JhiBase64Service","filePath":"/Users/milandeket/work/upwork/node_modules/ng-jhipster/src/service/base64.service.d.ts"},{"__symbol":84,"name":"JhiAlertService","filePath":"/Users/milandeket/work/upwork/node_modules/ng-jhipster/src/service/alert.service.d.ts"},{"__symbol":85,"name":"Sanitizer","filePath":"/Users/milandeket/work/upwork/node_modules/@angular/core/core.d.ts"},{"__symbol":86,"name":"JhiLanguageService","filePath":"/Users/milandeket/work/upwork/node_modules/ng-jhipster/src/language/language.service.d.ts"},{"__symbol":87,"name":"JhiModuleConfig","filePath":"/Users/milandeket/work/upwork/node_modules/ng-jhipster/src/config.d.ts"},{"__symbol":88,"name":"CookieService","filePath":"/Users/milandeket/work/upwork/node_modules/ngx-cookie/src/cookie.service.d.ts"},{"__symbol":89,"name":"cookieServiceFactory","filePath":"/Users/milandeket/work/upwork/node_modules/ngx-cookie/src/cookie.factory.d.ts"},{"__symbol":90,"name":"NgbAlertModule","filePath":"/Users/milandeket/work/upwork/node_modules/@ng-bootstrap/ng-bootstrap/alert/alert.module.d.ts"},{"__symbol":91,"name":"NgbButtonsModule","filePath":"/Users/milandeket/work/upwork/node_modules/@ng-bootstrap/ng-bootstrap/buttons/radio.module.d.ts"},{"__symbol":92,"name":"NgbCollapseModule","filePath":"/Users/milandeket/work/upwork/node_modules/@ng-bootstrap/ng-bootstrap/collapse/collapse.module.d.ts"},{"__symbol":93,"name":"NgbProgressbarModule","filePath":"/Users/milandeket/work/upwork/node_modules/@ng-bootstrap/ng-bootstrap/progressbar/progressbar.module.d.ts"},{"__symbol":94,"name":"NgbTooltipModule","filePath":"/Users/milandeket/work/upwork/node_modules/@ng-bootstrap/ng-bootstrap/tooltip/tooltip.module.d.ts"},{"__symbol":95,"name":"NgbTypeaheadModule","filePath":"/Users/milandeket/work/upwork/node_modules/@ng-bootstrap/ng-bootstrap/typeahead/typeahead.module.d.ts"},{"__symbol":96,"name":"NgbAccordionModule","filePath":"/Users/milandeket/work/upwork/node_modules/@ng-bootstrap/ng-bootstrap/accordion/accordion.module.d.ts"},{"__symbol":97,"name":"NgbCarouselModule","filePath":"/Users/milandeket/work/upwork/node_modules/@ng-bootstrap/ng-bootstrap/carousel/carousel.module.d.ts"},{"__symbol":98,"name":"ɵba","filePath":"/Users/milandeket/work/upwork/node_modules/@angular/forms/forms.d.ts"},{"__symbol":99,"name":"NgbDatepickerModule","filePath":"/Users/milandeket/work/upwork/node_modules/@ng-bootstrap/ng-bootstrap/datepicker/datepicker.module.d.ts"},{"__symbol":100,"name":"NgbDropdownModule","filePath":"/Users/milandeket/work/upwork/node_modules/@ng-bootstrap/ng-bootstrap/dropdown/dropdown.module.d.ts"},{"__symbol":101,"name":"NgbPaginationModule","filePath":"/Users/milandeket/work/upwork/node_modules/@ng-bootstrap/ng-bootstrap/pagination/pagination.module.d.ts"},{"__symbol":102,"name":"NgbPopoverModule","filePath":"/Users/milandeket/work/upwork/node_modules/@ng-bootstrap/ng-bootstrap/popover/popover.module.d.ts"},{"__symbol":103,"name":"NgbRatingModule","filePath":"/Users/milandeket/work/upwork/node_modules/@ng-bootstrap/ng-bootstrap/rating/rating.module.d.ts"},{"__symbol":104,"name":"NgbTabsetModule","filePath":"/Users/milandeket/work/upwork/node_modules/@ng-bootstrap/ng-bootstrap/tabset/tabset.module.d.ts"},{"__symbol":105,"name":"NgbTimepickerModule","filePath":"/Users/milandeket/work/upwork/node_modules/@ng-bootstrap/ng-bootstrap/timepicker/timepicker.module.d.ts"},{"__symbol":106,"name":"TranslateModule","filePath":"/Users/milandeket/work/upwork/node_modules/@ngx-translate/core/index.d.ts"},{"__symbol":107,"name":"NgbModule","filePath":"/Users/milandeket/work/upwork/node_modules/@ng-bootstrap/ng-bootstrap/index.d.ts"},{"__symbol":108,"name":"ɵbf","filePath":"/Users/milandeket/work/upwork/node_modules/@angular/forms/forms.d.ts"},{"__symbol":109,"name":"NgSelectOption","filePath":"/Users/milandeket/work/upwork/node_modules/@angular/forms/forms.d.ts"},{"__symbol":110,"name":"ɵq","filePath":"/Users/milandeket/work/upwork/node_modules/@angular/forms/forms.d.ts"},{"__symbol":111,"name":"DefaultValueAccessor","filePath":"/Users/milandeket/work/upwork/node_modules/@angular/forms/forms.d.ts"},{"__symbol":112,"name":"ɵbc","filePath":"/Users/milandeket/work/upwork/node_modules/@angular/forms/forms.d.ts"},{"__symbol":113,"name":"ɵbe","filePath":"/Users/milandeket/work/upwork/node_modules/@angular/forms/forms.d.ts"},{"__symbol":114,"name":"CheckboxControlValueAccessor","filePath":"/Users/milandeket/work/upwork/node_modules/@angular/forms/forms.d.ts"},{"__symbol":115,"name":"SelectControlValueAccessor","filePath":"/Users/milandeket/work/upwork/node_modules/@angular/forms/forms.d.ts"},{"__symbol":116,"name":"SelectMultipleControlValueAccessor","filePath":"/Users/milandeket/work/upwork/node_modules/@angular/forms/forms.d.ts"},{"__symbol":117,"name":"RadioControlValueAccessor","filePath":"/Users/milandeket/work/upwork/node_modules/@angular/forms/forms.d.ts"},{"__symbol":118,"name":"NgControlStatus","filePath":"/Users/milandeket/work/upwork/node_modules/@angular/forms/forms.d.ts"},{"__symbol":119,"name":"NgControlStatusGroup","filePath":"/Users/milandeket/work/upwork/node_modules/@angular/forms/forms.d.ts"},{"__symbol":120,"name":"RequiredValidator","filePath":"/Users/milandeket/work/upwork/node_modules/@angular/forms/forms.d.ts"},{"__symbol":121,"name":"MinLengthValidator","filePath":"/Users/milandeket/work/upwork/node_modules/@angular/forms/forms.d.ts"},{"__symbol":122,"name":"MaxLengthValidator","filePath":"/Users/milandeket/work/upwork/node_modules/@angular/forms/forms.d.ts"},{"__symbol":123,"name":"PatternValidator","filePath":"/Users/milandeket/work/upwork/node_modules/@angular/forms/forms.d.ts"},{"__symbol":124,"name":"CheckboxRequiredValidator","filePath":"/Users/milandeket/work/upwork/node_modules/@angular/forms/forms.d.ts"},{"__symbol":125,"name":"EmailValidator","filePath":"/Users/milandeket/work/upwork/node_modules/@angular/forms/forms.d.ts"},{"__symbol":126,"name":"NgModel","filePath":"/Users/milandeket/work/upwork/node_modules/@angular/forms/forms.d.ts"},{"__symbol":127,"name":"NgModelGroup","filePath":"/Users/milandeket/work/upwork/node_modules/@angular/forms/forms.d.ts"},{"__symbol":128,"name":"NgForm","filePath":"/Users/milandeket/work/upwork/node_modules/@angular/forms/forms.d.ts"},{"__symbol":129,"name":"NgClass","filePath":"/Users/milandeket/work/upwork/node_modules/@angular/common/common.d.ts"},{"__symbol":130,"name":"NgComponentOutlet","filePath":"/Users/milandeket/work/upwork/node_modules/@angular/common/common.d.ts"},{"__symbol":131,"name":"NgForOf","filePath":"/Users/milandeket/work/upwork/node_modules/@angular/common/common.d.ts"},{"__symbol":132,"name":"NgIf","filePath":"/Users/milandeket/work/upwork/node_modules/@angular/common/common.d.ts"},{"__symbol":133,"name":"NgTemplateOutlet","filePath":"/Users/milandeket/work/upwork/node_modules/@angular/common/common.d.ts"},{"__symbol":134,"name":"NgStyle","filePath":"/Users/milandeket/work/upwork/node_modules/@angular/common/common.d.ts"},{"__symbol":135,"name":"NgSwitch","filePath":"/Users/milandeket/work/upwork/node_modules/@angular/common/common.d.ts"},{"__symbol":136,"name":"NgSwitchCase","filePath":"/Users/milandeket/work/upwork/node_modules/@angular/common/common.d.ts"},{"__symbol":137,"name":"NgSwitchDefault","filePath":"/Users/milandeket/work/upwork/node_modules/@angular/common/common.d.ts"},{"__symbol":138,"name":"NgPlural","filePath":"/Users/milandeket/work/upwork/node_modules/@angular/common/common.d.ts"},{"__symbol":139,"name":"NgPluralCase","filePath":"/Users/milandeket/work/upwork/node_modules/@angular/common/common.d.ts"},{"__symbol":140,"name":"NgbAccordion","filePath":"/Users/milandeket/work/upwork/node_modules/@ng-bootstrap/ng-bootstrap/accordion/accordion.d.ts"},{"__symbol":141,"name":"NgbPanel","filePath":"/Users/milandeket/work/upwork/node_modules/@ng-bootstrap/ng-bootstrap/accordion/accordion.d.ts"},{"__symbol":142,"name":"NgbPanelTitle","filePath":"/Users/milandeket/work/upwork/node_modules/@ng-bootstrap/ng-bootstrap/accordion/accordion.d.ts"},{"__symbol":143,"name":"NgbPanelContent","filePath":"/Users/milandeket/work/upwork/node_modules/@ng-bootstrap/ng-bootstrap/accordion/accordion.d.ts"},{"__symbol":144,"name":"NgbRadio","filePath":"/Users/milandeket/work/upwork/node_modules/@ng-bootstrap/ng-bootstrap/buttons/radio.d.ts"},{"__symbol":145,"name":"NgbActiveLabel","filePath":"/Users/milandeket/work/upwork/node_modules/@ng-bootstrap/ng-bootstrap/buttons/radio.d.ts"},{"__symbol":146,"name":"NgbRadioGroup","filePath":"/Users/milandeket/work/upwork/node_modules/@ng-bootstrap/ng-bootstrap/buttons/radio.d.ts"},{"__symbol":147,"name":"NgbCarousel","filePath":"/Users/milandeket/work/upwork/node_modules/@ng-bootstrap/ng-bootstrap/carousel/carousel.d.ts"},{"__symbol":148,"name":"NgbSlide","filePath":"/Users/milandeket/work/upwork/node_modules/@ng-bootstrap/ng-bootstrap/carousel/carousel.d.ts"},{"__symbol":149,"name":"NgbCollapse","filePath":"/Users/milandeket/work/upwork/node_modules/@ng-bootstrap/ng-bootstrap/collapse/collapse.d.ts"},{"__symbol":150,"name":"NgbInputDatepicker","filePath":"/Users/milandeket/work/upwork/node_modules/@ng-bootstrap/ng-bootstrap/datepicker/datepicker-input.d.ts"},{"__symbol":151,"name":"NgbDropdownToggle","filePath":"/Users/milandeket/work/upwork/node_modules/@ng-bootstrap/ng-bootstrap/dropdown/dropdown.d.ts"},{"__symbol":152,"name":"NgbDropdown","filePath":"/Users/milandeket/work/upwork/node_modules/@ng-bootstrap/ng-bootstrap/dropdown/dropdown.d.ts"},{"__symbol":153,"name":"NgbPagination","filePath":"/Users/milandeket/work/upwork/node_modules/@ng-bootstrap/ng-bootstrap/pagination/pagination.d.ts"},{"__symbol":154,"name":"NgbPopover","filePath":"/Users/milandeket/work/upwork/node_modules/@ng-bootstrap/ng-bootstrap/popover/popover.d.ts"},{"__symbol":155,"name":"NgbProgressbar","filePath":"/Users/milandeket/work/upwork/node_modules/@ng-bootstrap/ng-bootstrap/progressbar/progressbar.d.ts"},{"__symbol":156,"name":"NgbRating","filePath":"/Users/milandeket/work/upwork/node_modules/@ng-bootstrap/ng-bootstrap/rating/rating.d.ts"},{"__symbol":157,"name":"NgbTabset","filePath":"/Users/milandeket/work/upwork/node_modules/@ng-bootstrap/ng-bootstrap/tabset/tabset.d.ts"},{"__symbol":158,"name":"NgbTab","filePath":"/Users/milandeket/work/upwork/node_modules/@ng-bootstrap/ng-bootstrap/tabset/tabset.d.ts"},{"__symbol":159,"name":"NgbTabContent","filePath":"/Users/milandeket/work/upwork/node_modules/@ng-bootstrap/ng-bootstrap/tabset/tabset.d.ts"},{"__symbol":160,"name":"NgbTabTitle","filePath":"/Users/milandeket/work/upwork/node_modules/@ng-bootstrap/ng-bootstrap/tabset/tabset.d.ts"},{"__symbol":161,"name":"NgbTimepicker","filePath":"/Users/milandeket/work/upwork/node_modules/@ng-bootstrap/ng-bootstrap/timepicker/timepicker.d.ts"},{"__symbol":162,"name":"NgbTooltip","filePath":"/Users/milandeket/work/upwork/node_modules/@ng-bootstrap/ng-bootstrap/tooltip/tooltip.d.ts"},{"__symbol":163,"name":"NgbTypeahead","filePath":"/Users/milandeket/work/upwork/node_modules/@ng-bootstrap/ng-bootstrap/typeahead/typeahead.d.ts"},{"__symbol":164,"name":"TranslateDirective","filePath":"/Users/milandeket/work/upwork/node_modules/@ngx-translate/core/src/translate.directive.d.ts"},{"__symbol":165,"name":"JhiMaxbytesValidatorDirective","filePath":"/Users/milandeket/work/upwork/node_modules/ng-jhipster/src/directive/maxbytes.directive.d.ts"},{"__symbol":166,"name":"JhiMinbytesValidatorDirective","filePath":"/Users/milandeket/work/upwork/node_modules/ng-jhipster/src/directive/minbytes.directive.d.ts"},{"__symbol":167,"name":"JhiSortDirective","filePath":"/Users/milandeket/work/upwork/node_modules/ng-jhipster/src/directive/sort.directive.d.ts"},{"__symbol":168,"name":"JhiSortByDirective","filePath":"/Users/milandeket/work/upwork/node_modules/ng-jhipster/src/directive/sort-by.directive.d.ts"},{"__symbol":169,"name":"JhiItemCountComponent","filePath":"/Users/milandeket/work/upwork/node_modules/ng-jhipster/src/component/jhi-item-count.component.d.ts"},{"__symbol":170,"name":"JhiTranslateComponent","filePath":"/Users/milandeket/work/upwork/node_modules/ng-jhipster/src/language/jhi-translate.directive.d.ts"},{"__symbol":171,"name":"ɵa","filePath":"/Users/milandeket/work/upwork/node_modules/ngx-infinite-scroll/index.d.ts"},{"__symbol":172,"name":"AsyncPipe","filePath":"/Users/milandeket/work/upwork/node_modules/@angular/common/common.d.ts"},{"__symbol":173,"name":"UpperCasePipe","filePath":"/Users/milandeket/work/upwork/node_modules/@angular/common/common.d.ts"},{"__symbol":174,"name":"LowerCasePipe","filePath":"/Users/milandeket/work/upwork/node_modules/@angular/common/common.d.ts"},{"__symbol":175,"name":"JsonPipe","filePath":"/Users/milandeket/work/upwork/node_modules/@angular/common/common.d.ts"},{"__symbol":176,"name":"SlicePipe","filePath":"/Users/milandeket/work/upwork/node_modules/@angular/common/common.d.ts"},{"__symbol":177,"name":"DecimalPipe","filePath":"/Users/milandeket/work/upwork/node_modules/@angular/common/common.d.ts"},{"__symbol":178,"name":"PercentPipe","filePath":"/Users/milandeket/work/upwork/node_modules/@angular/common/common.d.ts"},{"__symbol":179,"name":"TitleCasePipe","filePath":"/Users/milandeket/work/upwork/node_modules/@angular/common/common.d.ts"},{"__symbol":180,"name":"CurrencyPipe","filePath":"/Users/milandeket/work/upwork/node_modules/@angular/common/common.d.ts"},{"__symbol":181,"name":"I18nPluralPipe","filePath":"/Users/milandeket/work/upwork/node_modules/@angular/common/common.d.ts"},{"__symbol":182,"name":"I18nSelectPipe","filePath":"/Users/milandeket/work/upwork/node_modules/@angular/common/common.d.ts"},{"__symbol":183,"name":"TranslatePipe","filePath":"/Users/milandeket/work/upwork/node_modules/@ngx-translate/core/src/translate.pipe.d.ts"},{"__symbol":184,"name":"JhiCapitalizePipe","filePath":"/Users/milandeket/work/upwork/node_modules/ng-jhipster/src/pipe/capitalize.pipe.d.ts"},{"__symbol":185,"name":"JhiFilterPipe","filePath":"/Users/milandeket/work/upwork/node_modules/ng-jhipster/src/pipe/filter.pipe.d.ts"},{"__symbol":186,"name":"JhiKeysPipe","filePath":"/Users/milandeket/work/upwork/node_modules/ng-jhipster/src/pipe/keys.pipe.d.ts"},{"__symbol":187,"name":"JhiOrderByPipe","filePath":"/Users/milandeket/work/upwork/node_modules/ng-jhipster/src/pipe/order-by.pipe.d.ts"},{"__symbol":188,"name":"JhiPureFilterPipe","filePath":"/Users/milandeket/work/upwork/node_modules/ng-jhipster/src/pipe/pure-filter.pipe.d.ts"},{"__symbol":189,"name":"JhiTruncateCharactersPipe","filePath":"/Users/milandeket/work/upwork/node_modules/ng-jhipster/src/pipe/truncate-characters.pipe.d.ts"},{"__symbol":190,"name":"JhiTruncateWordsPipe","filePath":"/Users/milandeket/work/upwork/node_modules/ng-jhipster/src/pipe/truncate-words.pipe.d.ts"}]}